LICENSE
MANIFEST.in
README-ja.html
README-ja.rst
README.html
README.rst
setup.py
suzu/__init__.py
suzu/atomtbl.py
suzu/layer_elem.py
suzu/model.py
suzu/param1.py
suzu/param2.py
suzu/profile.py
suzu/proj.py
suzu/root.py
suzu/run.py
suzu/target.py
suzu/to_trim.py
suzu/version.py
suzu.egg-info/PKG-INFO
suzu.egg-info/SOURCES.txt
suzu.egg-info/dependency_links.txt
suzu.egg-info/entry_points.txt
suzu.egg-info/requires.txt
suzu.egg-info/top_level.txt
suzu/config/__init__.py
suzu/config/v0.py
suzu/config/v1.py
suzu/context/__init__.py
suzu/context/v0.py
suzu/context/v1.py
suzu/context/v2.py
suzu/db/__init__.py
suzu/db/disp.py
suzu/doc/faq.html
suzu/doc/faq.rst
suzu/doc/for_developpers.html
suzu/doc/for_developpers.rst
suzu/doc/packaging.html
suzu/doc/packaging.rst
suzu/doc/todo.html
suzu/doc/todo.rst
suzu/doc/virtualenv_win.html
suzu/doc/virtualenv_win.rst
suzu/matdb/__init__.py
suzu/matdb/autoscrolled.py
suzu/matdb/matdb.py
suzu/matdb/matdb_frame.py
suzu/matdb/srim_compounddb.py
suzu/matdb/srim_matdb.py
suzu/matdb/srim_matdb_frame.py
suzu/physics/__init__.py
suzu/physics/element.py
suzu/tktool/__init__.py
suzu/tktool/_truncatedentry.py
suzu/tktool/codedoptionmenu.py
suzu/tktool/error.py
suzu/tktool/filepathentry.py
suzu/tktool/gui_abstract.py
suzu/tktool/gui_testframe.py
suzu/tktool/oneof.py
suzu/tktool/test_error.py
suzu/tktool/validateentry.py