Metadata-Version: 1.1
Name: suzu
Version: 0.4.1
Summary: fake UI program for SRIM parameter input program (tin.exe)
Home-page: https://github.com/takaakiaoki/suzu
Author: Takaaki AOKI
Author-email: aoki.takaaki.6v@kyoto-u.ac.jp
License: UNKNOWN
Download-URL: http://sakura.nucleng.kyoto-u.ac.jp/~aoki/hg/suzu/
Platform: UNKNOWN
Classifier: Programming Language :: Python
Classifier: Programming Language :: Python :: 3.3
Classifier: License :: OSI Approved :: MIT License
Classifier: Development Status :: 4 - Beta
Classifier: Environment :: Other Environment
Classifier: Intended Audience :: Science/Research
Classifier: Operating System :: OS Independent
Classifier: Topic :: Scientific/Engineering :: Physics
